verilog/project.v
`timescale 1ns/10ps
module HA (A,B,Sum,Carry);
input A,B;
output Sum,Carry;
	xor (Sum,A,B);
	and (Carry,A,B);
endmodule

module FA (A,B,C,Sum,Carry);
input A,B,C;
output Sum,Carry;
	HA ha1(A,B,S1,C1);
	HA ha2(A,B,Sum,C2);
	or (Carry,C2,C1);
endmodule


module project (A0,A1,A2,A3,B0,B1,B2,B3,P0,P1,P2,P3,P4,P5,P6,C5);

input A0,A1,A2,A3,B0,B1,B2,B3;
output P0,P1,P2,P3,P4,P5,P6,C5;
wire l26,l43 ,l51,in1 ,l27 ,l61;
and(in1,A3,B3);
and(in2,A3,B2);
and(in3,A2,B3);
and(in4,A1,B3);
and(in5,A3,B1);
and(in6,A2,B2);
and(in7,A2,B1);
and(in8,A3,B0);	
and(in9,A0,B3);
and(in10,A1,B2);	
and(in11,A1,B1);
and(in12,A2,B0);
and(in13,A0,B2);
and(in14,A1,B0);
and(in15,A0,B1);
and(P0,A0,B0);
 
HA ha1(in15,in14,P1 ,l21);
HA ha2(in12,in11,l22,l23);
FA fa1(l22 ,in13,l21,P2 ,l31);
FA fa2(l24 ,in10,l23,l32,l33);
FA fa3(in9 ,l32 ,l31,P3 ,l41);
HA ha3(in7 ,in8 ,l24,l25);
FA fa4(in5 ,in6 ,l25,l34,l35);
FA fa5(in2 ,in3 ,l35,l26,l27);
FA fa6(in4 ,l34 ,l33,l42,l43);
HA ha4(l42 ,l41 ,P4 ,l51);
FA fa7(l26 ,l43 ,l51,P5,l61);
FA fa8(in1 ,l27 ,l61,P6,C5); 
endmodule

verilog/project_tb.v
`timescale 1ns/10ps

module project_tb;

reg A0,A1,A2,A3,B0,B1,B2,B3;
wire P0,P1 ,P2, P3, P4, P5, P6, C5;
integer i;
integer k;
project UUT (A0,A1,A2,A3,B0,B1,B2,B3,P0, P1, P2, P3, P4, P5 ,P6, C5); 

initial
    begin
        $dumpfile("project_tb.vcd");
        $dumpvars(0,project_tb);
	
		k=0;
        A0=0;
        A1=0; 
        A2=0; 
        A3=0; 
        B0=0; 
        B1=0; 
        B2=0; 
        B3=0;
        
    end

initial
    begin
        
        for( i = 1; i<=256;i = i+1)begin
        	#10
        	k = i;
        	A0=k%2;
        	k = k/2;
       		A1=k%2; 
       		k = k/2;
       		A2=k%2; 
       		k = k/2;
       		A3=k%2; 
       		k = k/2;
        	B0=k%2; 
        	k = k/2;
        	B1=k%2; 
        	k = k/2;
        	B2=k%2; 
        	k = k/2;
        	B3=k%2; 
        	
	end
    end

endmodule

verilog/project_tb.vcd
$date
	Mon Nov 28 18:58:19 2022
$end
$version
	Icarus Verilog
$end
$timescale
	10ps
$end
$scope module project_tb $end
$var wire 1 ! P6 $end
$var wire 1 " P5 $end
$var wire 1 # P4 $end
$var wire 1 $ P3 $end
$var wire 1 % P2 $end
$var wire 1 & P1 $end
$var wire 1 ' P0 $end
$var wire 1 ( C5 $end
$var reg 1 ) A0 $end
$var reg 1 * A1 $end
$var reg 1 + A2 $end
$var reg 1 , A3 $end
$var reg 1 - B0 $end
$var reg 1 . B1 $end
$var reg 1 / B2 $end
$var reg 1 0 B3 $end
$var integer 32 1 i [31:0] $end
$var integer 32 2 k [31:0] $end
$scope module UUT $end
$var wire 1 ) A0 $end
$var wire 1 * A1 $end
$var wire 1 + A2 $end
$var wire 1 , A3 $end
$var wire 1 - B0 $end
$var wire 1 . B1 $end
$var wire 1 / B2 $end
$var wire 1 0 B3 $end
$var wire 1 ' P0 $end
$var wire 1 3 in1 $end
$var wire 1 4 in10 $end
$var wire 1 5 in11 $end
$var wire 1 6 in12 $end
$var wire 1 7 in13 $end
$var wire 1 8 in14 $end
$var wire 1 9 in15 $end
$var wire 1 : in2 $end
$var wire 1 ; in3 $end
$var wire 1 < in4 $end
$var wire 1 = in5 $end
$var wire 1 > in6 $end
$var wire 1 ? in7 $end
$var wire 1 @ in8 $end
$var wire 1 A in9 $end
$var wire 1 B l61 $end
$var wire 1 C l51 $end
$var wire 1 D l43 $end
$var wire 1 E l42 $end
$var wire 1 F l41 $end
$var wire 1 G l35 $end
$var wire 1 H l34 $end
$var wire 1 I l33 $end
$var wire 1 J l32 $end
$var wire 1 K l31 $end
$var wire 1 L l27 $end
$var wire 1 M l26 $end
$var wire 1 N l25 $end
$var wire 1 O l24 $end
$var wire 1 P l23 $end
$var wire 1 Q l22 $end
$var wire 1 R l21 $end
$var wire 1 ! P6 $end
$var wire 1 " P5 $end
$var wire 1 # P4 $end
$var wire 1 $ P3 $end
$var wire 1 % P2 $end
$var wire 1 & P1 $end
$var wire 1 ( C5 $end
$scope module fa1 $end
$var wire 1 7 B $end
$var wire 1 K Carry $end
$var wire 1 % Sum $end
$var wire 1 S S1 $end
$var wire 1 T C2 $end
$var wire 1 U C1 $end
$var wire 1 R C $end
$var wire 1 Q A $end
$scope module ha1 $end
$var wire 1 7 B $end
$var wire 1 U Carry $end
$var wire 1 S Sum $end
$var wire 1 Q A $end
$upscope $end
$scope module ha2 $end
$var wire 1 7 B $end
$var wire 1 T Carry $end
$var wire 1 % Sum $end
$var wire 1 Q A $end
$upscope $end
$upscope $end
$scope module fa2 $end
$var wire 1 4 B $end
$var wire 1 I Carry $end
$var wire 1 J Sum $end
$var wire 1 V S1 $end
$var wire 1 W C2 $end
$var wire 1 X C1 $end
$var wire 1 P C $end
$var wire 1 O A $end
$scope module ha1 $end
$var wire 1 4 B $end
$var wire 1 X Carry $end
$var wire 1 V Sum $end
$var wire 1 O A $end
$upscope $end
$scope module ha2 $end
$var wire 1 4 B $end
$var wire 1 W Carry $end
$var wire 1 J Sum $end
$var wire 1 O A $end
$upscope $end
$upscope $end
$scope module fa3 $end
$var wire 1 A A $end
$var wire 1 J B $end
$var wire 1 K C $end
$var wire 1 F Carry $end
$var wire 1 $ Sum $end
$var wire 1 Y S1 $end
$var wire 1 Z C2 $end
$var wire 1 [ C1 $end
$scope module ha1 $end
$var wire 1 A A $end
$var wire 1 J B $end
$var wire 1 [ Carry $end
$var wire 1 Y Sum $end
$upscope $end
$scope module ha2 $end
$var wire 1 A A $end
$var wire 1 J B $end
$var wire 1 Z Carry $end
$var wire 1 $ Sum $end
$upscope $end
$upscope $end
$scope module fa4 $end
$var wire 1 = A $end
$var wire 1 > B $end
$var wire 1 G Carry $end
$var wire 1 H Sum $end
$var wire 1 \ S1 $end
$var wire 1 ] C2 $end
$var wire 1 ^ C1 $end
$var wire 1 N C $end
$scope module ha1 $end
$var wire 1 = A $end
$var wire 1 > B $end
$var wire 1 ^ Carry $end
$var wire 1 \ Sum $end
$upscope $end
$scope module ha2 $end
$var wire 1 = A $end
$var wire 1 > B $end
$var wire 1 ] Carry $end
$var wire 1 H Sum $end
$upscope $end
$upscope $end
$scope module fa5 $end
$var wire 1 : A $end
$var wire 1 ; B $end
$var wire 1 G C $end
$var wire 1 L Carry $end
$var wire 1 M Sum $end
$var wire 1 _ S1 $end
$var wire 1 ` C2 $end
$var wire 1 a C1 $end
$scope module ha1 $end
$var wire 1 : A $end
$var wire 1 ; B $end
$var wire 1 a Carry $end
$var wire 1 _ Sum $end
$upscope $end
$scope module ha2 $end
$var wire 1 : A $end
$var wire 1 ; B $end
$var wire 1 ` Carry $end
$var wire 1 M Sum $end
$upscope $end
$upscope $end
$scope module fa6 $end
$var wire 1 < A $end
$var wire 1 H B $end
$var wire 1 I C $end
$var wire 1 D Carry $end
$var wire 1 E Sum $end
$var wire 1 b S1 $end
$var wire 1 c C2 $end
$var wire 1 d C1 $end
$scope module ha1 $end
$var wire 1 < A $end
$var wire 1 H B $end
$var wire 1 d Carry $end
$var wire 1 b Sum $end
$upscope $end
$scope module ha2 $end
$var wire 1 < A $end
$var wire 1 H B $end
$var wire 1 c Carry $end
$var wire 1 E Sum $end
$upscope $end
$upscope $end
$scope module fa7 $end
$var wire 1 M A $end
$var wire 1 D B $end
$var wire 1 B Carry $end
$var wire 1 " Sum $end
$var wire 1 e S1 $end
$var wire 1 f C2 $end
$var wire 1 g C1 $end
$var wire 1 C C $end
$scope module ha1 $end
$var wire 1 M A $end
$var wire 1 D B $end
$var wire 1 g Carry $end
$var wire 1 e Sum $end
$upscope $end
$scope module ha2 $end
$var wire 1 M A $end
$var wire 1 D B $end
$var wire 1 f Carry $end
$var wire 1 " Sum $end
$upscope $end
$upscope $end
$scope module fa8 $end
$var wire 1 3 A $end
$var wire 1 L B $end
$var wire 1 B C $end
$var wire 1 ( Carry $end
$var wire 1 ! Sum $end
$var wire 1 h S1 $end
$var wire 1 i C2 $end
$var wire 1 j C1 $end
$scope module ha1 $end
$var wire 1 3 A $end
$var wire 1 L B $end
$var wire 1 j Carry $end
$var wire 1 h Sum $end
$upscope $end
$scope module ha2 $end
$var wire 1 3 A $end
$var wire 1 L B $end
$var wire 1 i Carry $end
$var wire 1 ! Sum $end
$upscope $end
$upscope $end
$scope module ha1 $end
$var wire 1 9 A $end
$var wire 1 8 B $end
$var wire 1 R Carry $end
$var wire 1 & Sum $end
$upscope $end
$scope module ha2 $end
$var wire 1 6 A $end
$var wire 1 5 B $end
$var wire 1 P Carry $end
$var wire 1 Q Sum $end
$upscope $end
$scope module ha3 $end
$var wire 1 ? A $end
$var wire 1 @ B $end
$var wire 1 N Carry $end
$var wire 1 O Sum $end
$upscope $end
$scope module ha4 $end
$var wire 1 E A $end
$var wire 1 F B $end
$var wire 1 C Carry $end
$var wire 1 # Sum $end
$upscope $end
$upscope $end
$upscope $end
$enddefinitions $end
#0
$dumpvars
0j
0i
0h
0g
0f
0e
0d
0c
0b
0a
0`
0_
0^
0]
0\
0[
0Z
0Y
0X
0W
0V
0U
0T
0S
0R
0Q
0P
0O
0N
0M
0L
0K
0J
0I
0H
0G
0F
0E
0D
0C
0B
0A
0@
0?
0>
0=
0<
0;
0:
09
08
07
06
05
04
03
b0 2
b1 1
00
0/
0.
0-
0,
0+
0*
0)
0(
0'
0&
0%
0$
0#
0"
0!
$end
#1000
b10 1
1)
b0 2
#2000
b11 1
1*
0)
b0 2
#3000
b100 1
1)
b0 2
#4000
b101 1
1+
0*
0)
b0 2
#5000
b110 1
1)
b0 2
#6000
b111 1
1*
0)
b0 2
#7000
b1000 1
1)
b0 2
#8000
b1001 1
1,
0+
0*
0)
b0 2
#9000
b1010 1
1)
b0 2
#10000
b1011 1
1*
0)
b0 2
#11000
b1100 1
1)
b0 2
#12000
b1101 1
1+
0*
0)
b0 2
#13000
b1110 1
1)
b0 2
#14000
b1111 1
1*
0)
b0 2
#15000
b10000 1
1)
b0 2
#16000
b10001 1
1-
0,
0+
0*
0)
b0 2
#17000
1'
b10010 1
1)
b0 2
#18000
1&
18
0'
b10011 1
1*
0)
b0 2
#19000
1'
b10100 1
1)
b0 2
#20000
1%
1S
1Q
0&
16
08
0'
b10101 1
1+
0*
0)
b0 2
#21000
1'
b10110 1
1)
b0 2
#22000
1&
18
0'
b10111 1
1*
0)
b0 2
#23000
1'
b11000 1
1)
b0 2
#24000
1Y
1$
1J
1V
0%
0S
1O
0Q
0&
1@
06
08
0'
b11001 1
1,
0+
0*
0)
b0 2
#25000
1'
b11010 1
1)
b0 2
#26000
1&
18
0'
b11011 1
1*
0)
b0 2
#27000
1'
b11100 1
1)
b0 2
#28000
1%
1S
1Q
0&
16
08
0'
b11101 1
1+
0*
0)
b0 2
#29000
1'
b11110 1
1)
b0 2
#30000
1&
18
0'
b11111 1
1*
0)
b0 2
#31000
1'
b100000 1
1)
b0 2
#32000
0Y
0$
0J
0V
0%
0S
0O
0Q
0&
0@
06
08
0'
b100001 1
1.
0-
0,
0+
0*
0)
b0 2
#33000
1&
19
b100010 1
1)
b0 2
#34000
1%
1S
1Q
0&
15
09
b100011 1
1*
0)
b0 2
#35000
1&
19
b100100 1
1)
b0 2
#36000
1Y
1$
1J
1V
0%
0S
1O
0Q
0&
1?
05
09
b100101 1
1+
0*
0)
b0 2
#37000
1&
19
b100110 1
1)
b0 2
#38000
1%
1S
1Q
0&
15
09
b100111 1
1*
0)
b0 2
#39000
1&
19
b101000 1
1)
b0 2
#40000
1#
0Y
0$
1b
1E
0J
0V
0%
0S
1\
1H
0O
0Q
0&
1=
0?
05
09
b101001 1
1,
0+
0*
0)
b0 2
#41000
1&
19
b101010 1
1)
b0 2
#42000
1%
1S
1Q
0&
15
09
b101011 1
1*
0)
b0 2
#43000
1&
19
b101100 1
1)
b0 2
#44000
1Y
1$
1J
1V
0%
0S
1O
0Q
0&
1?
05
09
b101101 1
1+
0*
0)
b0 2
#45000
1&
19
b101110 1
1)
b0 2
#46000
1%
1S
1Q
0&
15
09
b101111 1
1*
0)
b0 2
#47000
1&
19
b110000 1
1)
b0 2
#48000
0#
0Y
0$
0b
0E
0J
0V
0%
0S
0\
0H
0O
0Q
0&
0=
0?
05
09
b110001 1
1-
0,
0+
0*
0)
b0 2
#49000
1&
19
1'
b110010 1
1)
b0 2
#50000
1%
1S
1Q
15
18
09
0'
b110011 1
1*
0)
b0 2
#51000
0&
1R
19
1'
b110100 1
1)
b0 2
#52000
1Y
1$
1J
1V
1O
0R
1?
16
05
08
09
0'
b110101 1
1+
0*
0)
b0 2
#53000
1&
19
1'
b110110 1
1)
b0 2
#54000
0%
0S
0Q
1P
15
18
09
0'
b110111 1
1*
0)
b0 2
#55000
0&
1R
19
1'
b111000 1
1)
b0 2
#56000
1#
1b
1E
1\
1H
0P
0R
1=
1@
0?
06
05
08
09
0'
b111001 1
1,
0+
0*
0)
b0 2
#57000
1&
19
1'
b111010 1
1)
b0 2
#58000
1%
1S
1Q
15
18
09
0'
b111011 1
1*
0)
b0 2
#59000
0&
1R
19
1'
b111100 1
1)
b0 2
#60000
0Y
0$
0J
0V
0O
1N
0R
1?
16
05
08
09
0'
b111101 1
1+
0*
0)
b0 2
#61000
1&
19
1'
b111110 1
1)
b0 2
#62000
0%
0S
0Q
1P
15
18
09
0'
b111111 1
1*
0)
b0 2
#63000
0&
1R
19
1'
b1000000 1
1)
b0 2
#64000
0#
0b
0E
0\
0H
0N
0P
0R
0=
0@
0?
06
05
08
09
0'
b1000001 1
1/
0.
0-
0,
0+
0*
0)
b0 2
#65000
1S
1%
17
b1000010 1
1)
b0 2
#66000
1Y
1$
1V
1J
0S
0%
14
07
b1000011 1
1*
0)
b0 2
#67000
1S
1%
17
b1000100 1
1)
b0 2
#68000
1#
1b
1E
0Y
0$
1\
1H
0V
0J
0S
0%
1>
04
07
b1000101 1
1+
0*
0)
b0 2
#69000
1S
1%
17
b1000110 1
1)
b0 2
#70000
1Y
1$
1V
1J
0S
0%
14
07
b1000111 1
1*
0)
b0 2
#71000
1S
1%
17
b1001000 1
1)
b0 2
#72000
0#
1e
1"
0b
0E
0Y
0$
1_
1M
0\
0H
0V
0J
0S
0%
1:
0>
04
07
b1001001 1
1,
0+
0*
0)
b0 2
#73000
1S
1%
17
b1001010 1
1)
b0 2
#74000
1Y
1$
1V
1J
0S
0%
14
07
b1001011 1
1*
0)
b0 2
#75000
1S
1%
17
b1001100 1
1)
b0 2
#76000
1#
1b
1E
0Y
0$
1\
1H
0V
0J
0S
0%
1>
04
07
b1001101 1
1+
0*
0)
b0 2
#77000
1S
1%
17
b1001110 1
1)
b0 2
#78000
1Y
1$
1V
1J
0S
0%
14
07
b1001111 1
1*
0)
b0 2
#79000
1S
1%
17
b1010000 1
1)
b0 2
#80000
0#
0e
0"
0b
0E
0Y
0$
0_
0M
0\
0H
0V
0J
0S
0%
0:
0>
04
07
b1010001 1
1-
0,
0+
0*
0)
b0 2
#81000
1S
1%
17
1'
b1010010 1
1)
b0 2
#82000
1Y
1$
1V
1J
1&
0S
0%
14
18
07
0'
b1010011 1
1*
0)
b0 2
#83000
1S
1%
17
1'
b1010100 1
1)
b0 2
#84000
1#
1b
1E
0Y
0$
1\
1H
1Q
0V
0J
0&
1S
1%
1>
16
04
08
07
0'
b1010101 1
1+
0*
0)
b0 2
#85000
1K
0S
1U
0%
1T
17
1'
b1010110 1
1)
b0 2
#86000
1Y
1$
0K
1V
1J
1&
1S
0U
1%
0T
14
18
07
0'
b1010111 1
1*
0)
b0 2
#87000
1K
0S
1U
0%
1T
17
1'
b1011000 1
1)
b0 2
#88000
0#
1e
1"
0b
0E
1Y
1$
0K
1_
1M
1O
0\
0H
0Q
1V
1J
0&
0S
0U
0%
0T
1:
1@
0>
06
04
08
07
0'
b1011001 1
1,
0+
0*
0)
b0 2
#89000
1S
1%
17
1'
b1011010 1
1)
b0 2
#90000
0Y
0$
1I
0V
1X
0J
1W
1&
0S
0%
14
18
07
0'
b1011011 1
1*
0)
b0 2
#91000
1S
1%
17
1'
b1011100 1
1)
b0 2
#92000
1#
1b
1E
1Y
1$
0I
1\
1H
1Q
1V
0X
1J
0W
0&
1S
1%
1>
16
04
08
07
0'
b1011101 1
1+
0*
0)
b0 2
#93000
1K
0S
1U
0%
1T
17
1'
b1011110 1
1)
b0 2
#94000
0Y
0$
1I
0K
0V
1X
0J
1W
1&
1S
0U
1%
0T
14
18
07
0'
b1011111 1
1*
0)
b0 2
#95000
1K
0S
1U
0%
1T
17
1'
b1100000 1
1)
b0 2
#96000
0#
0e
0"
0b
0E
0Y
0$
0I
0K
0_
0M
0O
0\
0H
0Q
0V
0X
0J
0W
0&
0S
0U
0%
0T
0:
0@
0>
06
04
08
07
0'
b1100001 1
1.
0-
0,
0+
0*
0)
b0 2
#97000
1S
1%
1&
17
19
b1100010 1
1)
b0 2
#98000
1Y
1$
1V
1J
1Q
1S
1%
0&
14
15
07
09
b1100011 1
1*
0)
b0 2
#99000
1K
0S
1U
0%
1T
1&
17
19
b1100100 1
1)
b0 2
#100000
1#
1b
1E
1Y
1$
0K
1\
1H
1O
1V
1J
0Q
0S
0U
0%
0T
0&
1>
1?
04
05
07
09
b1100101 1
1+
0*
0)
b0 2
#101000
1S
1%
1&
17
19
b1100110 1
1)
b0 2
#102000
0Y
0$
1I
0V
1X
0J
1W
1Q
1S
1%
0&
14
15
07
09
b1100111 1
1*
0)
b0 2
#103000
1K
0S
1U
0%
1T
1&
17
19
b1101000 1
1)
b0 2
#104000
1e
1"
0Y
0$
0I
0K
1_
1M
0O
0V
0X
0J
0W
0Q
0S
0U
0%
0T
0&
1:
1=
0>
0?
04
05
07
09
b1101001 1
1,
0+
0*
0)
b0 2
#105000
1S
1%
1&
17
19
b1101010 1
1)
b0 2
#106000
1Y
1$
1V
1J
1Q
1S
1%
0&
14
15
07
09
b1101011 1
1*
0)
b0 2
#107000
1K
0S
1U
0%
1T
1&
17
19
b1101100 1
1)
b0 2
#108000
0#
0b
0E
1G
1Y
1$
0K
0\
1^
0H
1]
1O
1V
1J
0Q
0S
0U
0%
0T
0&
1>
1?
04
05
07
09
b1101101 1
1+
0*
0)
b0 2
#109000
1S
1%
1&
17
19
b1101110 1
1)
b0 2
#110000
0Y
0$
1I
0V
1X
0J
1W
1Q
1S
1%
0&
14
15
07
09
b1101111 1
1*
0)
b0 2
#111000
1K
0S
1U
0%
1T
1&
17
19
b1110000 1
1)
b0 2
#112000
0e
0"
0G
0Y
0$
0I
0K
0_
0M
0^
0]
0O
0V
0X
0J
0W
0Q
0S
0U
0%
0T
0&
0:
0=
0>
0?
04
05
07
09
b1110001 1
1-
0,
0+
0*
0)
b0 2
#113000
1S
1%
1&
17
19
1'
b1110010 1
1)
b0 2
#114000
1Y
1$
1V
1J
1Q
1S
1%
14
15
18
07
09
0'
b1110011 1
1*
0)
b0 2
#115000
1K
0S
1U
0%
1T
0&
1R
17
19
1'
b1110100 1
1)
b0 2
#116000
1#
1b
1E
1Y
1$
0K
1\
1H
1O
1V
1J
1S
0U
1%
0T
0R
1>
1?
16
04
05
08
07
09
0'
b1110101 1
1+
0*
0)
b0 2
#117000
1K
0S
1U
0%
1T
1&
17
19
1'
b1110110 1
1)
b0 2
#118000
0Y
0$
1I
0K
0V
1X
0J
1W
0Q
1P
0S
0U
0%
0T
14
15
18
07
09
0'
b1110111 1
1*
0)
b0 2
#119000
1S
1%
0&
1R
17
19
1'
b1111000 1
1)
b0 2
#120000
1e
1"
1Y
1$
0I
1_
1M
1V
0X
1J
0W
0P
0S
0%
0R
1:
1=
1@
0>
0?
06
04
05
08
07
09
0'
b1111001 1
1,
0+
0*
0)
b0 2
#121000
1S
1%
1&
17
19
1'
b1111010 1
1)
b0 2
#122000
0Y
0$
1I
0V
1X
0J
1W
1Q
1S
1%
14
15
18
07
09
0'
b1111011 1
1*
0)
b0 2
#123000
1K
0S
1U
0%
1T
0&
1R
17
19
1'
b1111100 1
1)
b0 2
#124000
0#
0b
0E
1G
0Y
0$
0I
0K
0\
1^
0H
1]
0O
1N
0V
0X
0J
0W
1S
0U
1%
0T
0R
1>
1?
16
04
05
08
07
09
0'
b1111101 1
1+
0*
0)
b0 2
#125000
1K
0S
1U
0%
1T
1&
17
19
1'
b1111110 1
1)
b0 2
#126000
1Y
1$
0K
1V
1J
0Q
1P
0S
0U
0%
0T
14
15
18
07
09
0'
b1111111 1
1*
0)
b0 2
#127000
1S
1%
0&
1R
17
19
1'
b10000000 1
1)
b0 2
#128000
0e
0"
0G
0Y
0$
0_
0M
0^
0]
0N
0V
0J
0P
0S
0%
0R
0:
0=
0@
0>
0?
06
04
05
08
07
09
0'
b10000001 1
10
0/
0.
0-
0,
0+
0*
0)
b1 2
#129000
1Y
1$
1A
b10000010 1
1)
b1 2
#130000
1#
1b
1E
0Y
0$
1<
0A
b10000011 1
1*
0)
b1 2
#131000
1Y
1$
1A
b10000100 1
1)
b1 2
#132000
1e
1"
0#
1_
1M
0b
0E
0Y
0$
1;
0<
0A
b10000101 1
1+
0*
0)
b1 2
#133000
1Y
1$
1A
b10000110 1
1)
b1 2
#134000
1#
1b
1E
0Y
0$
1<
0A
b10000111 1
1*
0)
b1 2
#135000
1Y
1$
1A
b10001000 1
1)
b1 2
#136000
0e
0"
0#
1h
1!
0_
0M
0b
0E
0Y
0$
13
0;
0<
0A
b10001001 1
1,
0+
0*
0)
b1 2
#137000
1Y
1$
1A
b10001010 1
1)
b1 2
#138000
1#
1b
1E
0Y
0$
1<
0A
b10001011 1
1*
0)
b1 2
#139000
1Y
1$
1A
b10001100 1
1)
b1 2
#140000
1e
1"
0#
1_
1M
0b
0E
0Y
0$
1;
0<
0A
b10001101 1
1+
0*
0)
b1 2
#141000
1Y
1$
1A
b10001110 1
1)
b1 2
#142000
1#
1b
1E
0Y
0$
1<
0A
b10001111 1
1*
0)
b1 2
#143000
1Y
1$
1A
b10010000 1
1)
b1 2
#144000
0e
0"
0#
0h
0!
0_
0M
0b
0E
0Y
0$
03
0;
0<
0A
b10010001 1
1-
0,
0+
0*
0)
b1 2
#145000
1Y
1$
1A
1'
b10010010 1
1)
b1 2
#146000
1#
1b
1E
1&
0Y
0$
1<
18
0A
0'
b10010011 1
1*
0)
b1 2
#147000
1Y
1$
1A
1'
b10010100 1
1)
b1 2
#148000
1e
1"
1%
1S
0#
1_
1M
1Q
0b
0E
0&
0Y
0$
1;
16
0<
08
0A
0'
b10010101 1
1+
0*
0)
b1 2
#149000
1Y
1$
1A
1'
b10010110 1
1)
b1 2
#150000
1#
1b
1E
1&
0Y
0$
1<
18
0A
0'
b10010111 1
1*
0)
b1 2
#151000
1Y
1$
1A
1'
b10011000 1
1)
b1 2
#152000
1J
1V
0e
0"
0%
0S
0#
1h
1!
1O
0_
0M
0Q
0b
0E
0&
1Y
1$
13
1@
0;
06
0<
08
0A
0'
b10011001 1
1,
0+
0*
0)
b1 2
#153000
1#
1F
0Y
1[
0$
1Z
1A
1'
b10011010 1
1)
b1 2
#154000
0F
1b
1E
1&
1Y
0[
1$
0Z
1<
18
0A
0'
b10011011 1
1*
0)
b1 2
#155000
0#
1C
1F
0Y
1[
0$
1Z
1A
1'
b10011100 1
1)
b1 2
#156000
1e
1"
1%
1S
0C
0F
1_
1M
1Q
0b
0E
0&
1Y
0[
1$
0Z
1;
16
0<
08
0A
0'
b10011101 1
1+
0*
0)
b1 2
#157000
1#
1F
0Y
1[
0$
1Z
1A
1'
b10011110 1
1)
b1 2
#158000
0F
1b
1E
1&
1Y
0[
1$
0Z
1<
18
0A
0'
b10011111 1
1*
0)
b1 2
#159000
0#
1C
1F
0Y
1[
0$
1Z
1A
1'
b10100000 1
1)
b1 2
#160000
0J
0V
0e
0"
0%
0S
0C
0F
0h
0!
0O
0_
0M
0Q
0b
0E
0&
0Y
0[
0$
0Z
03
0@
0;
06
0<
08
0A
0'
b10100001 1
1.
0-
0,
0+
0*
0)
b1 2
#161000
1Y
1$
1&
1A
19
b10100010 1
1)
b1 2
#162000
1#
1%
1S
1b
1E
1Q
0Y
0$
0&
1<
15
0A
09
b10100011 1
1*
0)
b1 2
#163000
1Y
1$
1&
1A
19
b10100100 1
1)
b1 2
#164000
1e
1"
1J
1V
0#
0%
0S
1_
1M
1O
0b
0E
0Q
1Y
1$
0&
1;
1?
0<
05
0A
09
b10100101 1
1+
0*
0)
b1 2
#165000
1#
1F
0Y
1[
0$
1Z
1&
1A
19
b10100110 1
1)
b1 2
#166000
1%
1S
0F
1b
1E
1Q
1Y
0[
1$
0Z
0&
1<
15
0A
09
b10100111 1
1*
0)
b1 2
#167000
0#
1C
1F
0Y
1[
0$
1Z
1&
1A
19
b10101000 1
1)
b1 2
#168000
1#
0e
0"
0J
0V
0C
0%
0S
0F
1h
1!
1\
1H
0_
0M
0O
1b
1E
0Q
0Y
0[
0$
0Z
0&
13
1=
0;
0?
0<
05
0A
09
b10101001 1
1,
0+
0*
0)
b1 2
#169000
1Y
1$
1&
1A
19
b10101010 1
1)
b1 2
#170000
1e
1"
0#
1D
1%
1S
0b
1d
0E
1c
1Q
0Y
0$
0&
1<
15
0A
09
b10101011 1
1*
0)
b1 2
#171000
1Y
1$
1&
1A
19
b10101100 1
1)
b1 2
#172000
1J
1V
1#
0D
0%
0S
1_
1M
1O
1b
0d
1E
0c
0Q
1Y
1$
0&
1;
1?
0<
05
0A
09
b10101101 1
1+
0*
0)
b1 2
#173000
0#
1C
1F
0Y
1[
0$
1Z
1&
1A
19
b10101110 1
1)
b1 2
#174000
1B
0e
1g
0"
1f
0C
1D
1%
1S
0F
0b
1d
0E
1c
1Q
1Y
0[
1$
0Z
0&
1<
15
0A
09
b10101111 1
1*
0)
b1 2
#175000
1#
1F
0Y
1[
0$
1Z
1&
1A
19
b10110000 1
1)
b1 2
#176000
0#
0B
0g
0f
0J
0V
0D
0%
0S
0F
0h
0!
0\
0H
0_
0M
0O
0b
0d
0E
0c
0Q
0Y
0[
0$
0Z
0&
03
0=
0;
0?
0<
05
0A
09
b10110001 1
1-
0,
0+
0*
0)
b1 2
#177000
1Y
1$
1&
1A
19
1'
b10110010 1
1)
b1 2
#178000
1#
1%
1S
1b
1E
1Q
0Y
0$
1<
15
18
0A
09
0'
b10110011 1
1*
0)
b1 2
#179000
1Y
1$
0&
1R
1A
19
1'
b10110100 1
1)
b1 2
#180000
1e
1"
1J
1V
0#
1_
1M
1O
0b
0E
1Y
1$
0R
1;
1?
16
0<
05
08
0A
09
0'
b10110101 1
1+
0*
0)
b1 2
#181000
1#
1F
0Y
1[
0$
1Z
1&
1A
19
1'
b10110110 1
1)
b1 2
#182000
0%
0S
0F
1b
1E
0Q
1P
1Y
0[
1$
0Z
1<
15
18
0A
09
0'
b10110111 1
1*
0)
b1 2
#183000
0#
1C
1F
0Y
1[
0$
1Z
0&
1R
1A
19
1'
b10111000 1
1)
b1 2
#184000
1#
0e
0"
0C
0F
1h
1!
1\
1H
0_
0M
1b
1E
0P
1Y
0[
1$
0Z
0R
13
1=
1@
0;
0?
06
0<
05
08
0A
09
0'
b10111001 1
1,
0+
0*
0)
b1 2
#185000
0#
1C
1F
0Y
1[
0$
1Z
1&
1A
19
1'
b10111010 1
1)
b1 2
#186000
1e
1"
0C
1D
1%
1S
0F
0b
1d
0E
1c
1Q
1Y
0[
1$
0Z
1<
15
18
0A
09
0'
b10111011 1
1*
0)
b1 2
#187000
1#
1F
0Y
1[
0$
1Z
0&
1R
1A
19
1'
b10111100 1
1)
b1 2
#188000
0J
0V
0D
0F
1_
1M
0O
1N
1b
0d
1E
0c
0Y
0[
0$
0Z
0R
1;
1?
16
0<
05
08
0A
09
0'
b10111101 1
1+
0*
0)
b1 2
#189000
1Y
1$
1&
1A
19
1'
b10111110 1
1)
b1 2
#190000
1B
0e
1g
0"
1f
0#
1D
0%
0S
0b
1d
0E
1c
0Q
1P
0Y
0$
1<
15
18
0A
09
0'
b10111111 1
1*
0)
b1 2
#191000
1Y
1$
0&
1R
1A
19
1'
b11000000 1
1)
b1 2
#192000
0B
0g
0f
0#
0D
0h
0!
0\
0H
0_
0M
0N
0b
0d
0E
0c
0P
0Y
0$
0R
03
0=
0@
0;
0?
06
0<
05
08
0A
09
0'
b11000001 1
1/
0.
0-
0,
0+
0*
0)
b1 2
#193000
1Y
1$
1S
1%
1A
17
b11000010 1
1)
b1 2
#194000
1#
1b
1E
1V
1J
1Y
1$
0S
0%
1<
14
0A
07
b11000011 1
1*
0)
b1 2
#195000
0#
1C
1F
0Y
1[
0$
1Z
1S
1%
1A
17
b11000100 1
1)
b1 2
#196000
1#
1e
1"
0C
0F
1_
1M
1\
1H
1b
1E
0V
0J
0Y
0[
0$
0Z
0S
0%
1;
1>
0<
04
0A
07
b11000101 1
1+
0*
0)
b1 2
#197000
1Y
1$
1S
1%
1A
17
b11000110 1
1)
b1 2
#198000
1B
0e
1g
0"
1f
0#
1D
0b
1d
0E
1c
1V
1J
1Y
1$
0S
0%
1<
14
0A
07
b11000111 1
1*
0)
b1 2
#199000
1#
1F
0Y
1[
0$
1Z
1S
1%
1A
17
b11001000 1
1)
b1 2
